bumps/__init__.py
bumps/__main__.py
bumps/_version.py
bumps/bounds.py
bumps/bspline.py
bumps/cheby.py
bumps/cli.py
bumps/curve.py
bumps/data.py
bumps/dump.py
bumps/errplot.py
bumps/fitproblem.py
bumps/fitservice.py
bumps/fitters.py
bumps/formatnum.py
bumps/history.py
bumps/initpop.py
bumps/lsqerror.py
bumps/mapper.py
bumps/monitor.py
bumps/mono.py
bumps/mpfit.py
bumps/names.py
bumps/options.py
bumps/parameter.py
bumps/partemp.py
bumps/pdfwrapper.py
bumps/plotutil.py
bumps/plugin.py
bumps/pmath.py
bumps/pymcfit.py
bumps/pytwalk.py
bumps/quasinewton.py
bumps/random_lines.py
bumps/serialize.py
bumps/simplex.py
bumps/util.py
bumps/wsolve.py
bumps/dream/__init__.py
bumps/dream/acr.py
bumps/dream/bounds.py
bumps/dream/build_compiled.py
bumps/dream/compiled.c
bumps/dream/compiled.py
bumps/dream/convergence.py
bumps/dream/core.py
bumps/dream/corrplot.py
bumps/dream/crossover.py
bumps/dream/diffev.py
bumps/dream/digits.py
bumps/dream/entropy.py
bumps/dream/exppow.py
bumps/dream/formatnum.py
bumps/dream/gelman.py
bumps/dream/geweke.py
bumps/dream/initpop.py
bumps/dream/ksmirnov.py
bumps/dream/mahal.py
bumps/dream/matlab.py
bumps/dream/metropolis.py
bumps/dream/model.py
bumps/dream/outliers.py
bumps/dream/parcoord.py
bumps/dream/state.py
bumps/dream/stats.py
bumps/dream/tile.py
bumps/dream/util.py
bumps/dream/varplot.py
bumps/dream/views.py
bumps/dream/walk.py
bumps/dream/random123/LICENSE
bumps/dream/random123/include/Random123/aes.h
bumps/dream/random123/include/Random123/array.h
bumps/dream/random123/include/Random123/ars.h
bumps/dream/random123/include/Random123/gsl_microrng.h
bumps/dream/random123/include/Random123/philox.h
bumps/dream/random123/include/Random123/threefry.h
bumps/dream/random123/include/Random123/u01fixedpt.h
bumps/dream/random123/include/Random123/conventional/gsl_cbrng.h
bumps/dream/random123/include/Random123/features/clangfeatures.h
bumps/dream/random123/include/Random123/features/compilerfeatures.h
bumps-1.0.3.dist-info/licenses/LICENSE.txt
bumps-1.0.3.dist-info/METADATA
bumps-1.0.3.dist-info/WHEEL
bumps-1.0.3.dist-info/entry_points.txt
bumps-1.0.3.dist-info/top_level.txt
bumps-1.0.3.dist-info/RECORD
