Metadata-Version: 2.4
Name: bumps
Version: 1.0.3
Summary: Data fitting with bayesian uncertainty analysis
Author-email: Paul Kienzle <paul.kienzle@nist.gov>
License: Bumps is in the public domain.
Project-URL: documentation, https://bumps.readthedocs.io
Project-URL: homepage, https://bumps.readthedocs.io
Project-URL: repository, https://github.com/bumps/bumps
Classifier: Development Status :: 4 - Beta
Classifier: Environment :: Console
Classifier: Intended Audience :: Science/Research
Classifier: License :: Public Domain
Classifier: Operating System :: OS Independent
Classifier: Programming Language :: Python
Classifier: Programming Language :: Python :: 3
Classifier: Topic :: Scientific/Engineering
Classifier: Topic :: Scientific/Engineering :: Chemistry
Classifier: Topic :: Scientific/Engineering :: Physics
Requires-Python: >=3.9
License-File: LICENSE.txt
Requires-Dist: numpy
Requires-Dist: scipy
Requires-Dist: h5py
Requires-Dist: dill
Requires-Dist: cloudpickle
Requires-Dist: matplotlib
Requires-Dist: blinker
Requires-Dist: aiohttp
Requires-Dist: python-socketio
Requires-Dist: plotly
Requires-Dist: mpld3
Requires-Dist: msgpack
Requires-Dist: graphlib_backport; python_version < "3.9"
Provides-Extra: dev
Requires-Dist: build; extra == "dev"
Requires-Dist: pre-commit; extra == "dev"
Requires-Dist: pytest; extra == "dev"
Requires-Dist: pytest-cov; extra == "dev"
Requires-Dist: ruff; extra == "dev"
Requires-Dist: wheel; extra == "dev"
Requires-Dist: setuptools; extra == "dev"
Requires-Dist: sphinx; extra == "dev"
Requires-Dist: versioningit; extra == "dev"
Dynamic: license-file
